{
  "type": "FeatureCollection",
  "features": [
    {
      "type": "Feature",
      "geometry": {
        "type": "Polygon",
        "coordinates": [
          [
            [
              41.384398341178894,
              67.79406665212267
            ],
            [
              27.849242091178894,
              71.28790923792681
            ],
            [
              22.224242091178894,
              70.94658711714413
            ],
            [
              14.665648341178894,
              68.70585633448827
            ],
            [
              9.919554591178894,
              63.68692038522694
            ],
            [
              4.470335841178894,
              62.16726330447897
            ],
            [
              7.458617091178894,
              57.68267689111488
            ],
            [
              10.798460841178894,
              59.603004383421414
            ],
            [
              12.732054591178894,
              56.440289207249165
            ],
            [
              16.247679591178894,
              56.3429920533593
            ],
            [
              17.478148341178894,
              58.7017355718427
            ],
            [
              19.060179591178894,
              60.13244236066634
            ],
            [
              17.126585841178894,
              61.67081460796758
            ],
            [
              22.224242091178894,
              65.78630513925268
            ],
            [
              25.564085841178894,
              65.64171087916328
            ],
            [
              21.521117091178894,
              62.736329054576004
            ],
            [
              22.575804591178894,
              60.044787344592955
            ],
            [
              27.673460841178894,
              60.653496280998446
            ],
            [
              31.892210841178894,
              63.056668712047646
            ],
            [
              29.607054591178894,
              67.99252204630979
            ],
            [
              41.384398341178894,
              67.79406665212267
            ]
          ]
        ]
      },
      "properties": {}
    },
    {
      "type": "Feature",
      "geometry": {
        "type": "Polygon",
        "coordinates": [
          [
            [
              9.91413136727806,
              57.301897922515195
            ],
            [
              6.92585011727806,
              55.94827552308168
            ],
            [
              9.03522511727806,
              54.03261683243158
            ],
            [
              5.34381886727806,
              53.19846305282762
            ],
            [
              -4.49993113272194,
              47.95939697802494
            ],
            [
              -0.9843061327219402,
              46.041589834868034
            ],
            [
              -1.5116498827219402,
              43.16391860202786
            ],
            [
              -8.19133738272194,
              43.035569301435146
            ],
            [
              -9.42180613272194,
              38.23688355157907
            ],
            [
              -4.67571238272194,
              35.8521016624935
            ],
            [
              1.3008501172780598,
              38.92394482312625
            ],
            [
              3.9375688672780598,
              43.41980985575781
            ],
            [
              7.80475636727806,
              42.77806375321207
            ],
            [
              9.38678761727806,
              44.807950564001544
            ],
            [
              15.71491261727806,
              39.19692608080463
            ],
            [
              12.90241261727806,
              38.09868361861733
            ],
            [
              16.06647511727806,
              36.27837647823222
            ],
            [
              18.52741261727806,
              40.14402744645582
            ],
            [
              12.37506886727806,
              44.807950564001544
            ],
            [
              14.66022511727806,
              46.7688377889987
            ],
            [
              19.05475636727806,
              42.1295970841181
            ],
            [
              22.04303761727806,
              36.8431397061644
            ],
            [
              25.344979071688613,
              37.431684069689595
            ],
            [
              23.235604071688613,
              40.37207486485184
            ],
            [
              26.487557196688613,
              40.37207486485184
            ],
            [
              29.036385321688613,
              40.9056223591982
            ],
            [
              28.421150946688613,
              42.86831265886065
            ],
            [
              31.145760321688613,
              46.370050874569955
            ],
            [
              33.60669782168861,
              45.76023961259143
            ],
            [
              33.87036969668861,
              44.52039931084803
            ],
            [
              36.68286969668861,
              44.89518255169577
            ],
            [
              35.01294782168861,
              46.18781477934748
            ],
            [
              38.70435407168861,
              46.91312393358134
            ],
            [
              40.72583844668861,
              49.31831687044891
            ],
            [
              34.04615094668861,
              52.26176778026771
            ],
            [
              31.848885321688613,
              52.74327374142746
            ],
            [
              30.882088446688613,
              55.5724425320514
            ],
            [
              27.893807196688613,
              56.74699848941589
            ],
            [
              28.509041571688613,
              59.350274170444386
            ],
            [
              23.762947821688613,
              58.98993286894622
            ],
            [
              24.466072821688613,
              56.89130154488339
            ],
            [
              22.708260321688613,
              57.557395128970924
            ],
            [
              21.038338446688613,
              56.55372868432192
            ],
            [
              21.302010321688613,
              54.81999328162417
            ],
            [
              19.544197821688613,
              54.36167574263668
            ],
            [
              17.962166571688613,
              54.769323598027434
            ],
            [
              15.149666571688613,
              53.94994193535108
            ],
            [
              13.040291571688613,
              54.15632081570204
            ],
            [
              11.282479071688613,
              53.94994193535108
            ],
            [
              10.491463446688613,
              54.97162155620366
            ],
            [
              9.91413136727806,
              57.301897922515195
            ]
          ]
        ]
      },
      "properties": {}
    },
    {
      "type": "Feature",
      "geometry": {
        "type": "Polygon",
        "coordinates": [
          [
            [
              26.63216433355649,
              40.01688559847615
            ],
            [
              30.93880495855649,
              40.952727686351885
            ],
            [
              33.48763308355649,
              42.07151772816733
            ],
            [
              35.50911745855649,
              41.87549002040491
            ],
            [
              40.16732058355649,
              40.819835340387705
            ],
            [
              41.83724245855649,
              41.81001340778677
            ],
            [
              39.99153933355649,
              43.61798160108266
            ],
            [
              48.51692995855649,
              41.54743719485284
            ],
            [
              50.27474245855649,
              40.68667621532592
            ],
            [
              48.86849245855649,
              38.175373972754706
            ],
            [
              51.68099245855649,
              36.35693985440585
            ],
            [
              54.40560183355649,
              37.41139864905477
            ],
            [
              57.04232058355649,
              38.313428522988836
            ],
            [
              61.26107058355649,
              36.498374648299716
            ],
            [
              63.37044558355649,
              26.47770061657752
            ],
            [
              61.52474245855649,
              25.291637291684616
            ],
            [
              57.30599245855649,
              26.00470657506738
            ],
            [
              50.97786745855649,
              28.040225996494485
            ],
            [
              49.92317995855649,
              30.265944691360474
            ],
            [
              47.98958620855649,
              29.35081610295127
            ],
            [
              51.59310183355649,
              24.2542245033813
            ],
            [
              56.16341433355649,
              25.52979999118705
            ],
            [
              59.76692995855649,
              22.398075990265564
            ],
            [
              57.04232058355649,
              18.195171159649078
            ],
            [
              49.74739870855649,
              14.655072053311576
            ],
            [
              43.33138308355649,
              12.776711985036426
            ],
            [
              41.83724245855649,
              17.693481280589605
            ],
            [
              37.88216433355649,
              23.933291187592587
            ],
            [
              35.33333620855649,
              27.962624216330624
            ],
            [
              34.45442995855649,
              31.547875867499663
            ],
            [
              36.38802370855649,
              36.92113034835576
            ],
            [
              34.45442995855649,
              36.63955158439511
            ],
            [
              32.60872683355649,
              36.14430504055285
            ],
            [
              30.67513308355649,
              36.63955158439511
            ],
            [
              29.18099245855649,
              36.14430504055285
            ],
            [
              26.80794558355649,
              38.106248417405304
            ],
            [
              26.63216433355649,
              40.01688559847615
            ]
          ]
        ]
      },
      "properties": {}
    }
  ]
}